dataculpa/__init__.py
dataculpa/connector.py
dataculpa/validator.py
dataculpa_client-1.4.1.dist-info/LICENSE
dataculpa_client-1.4.1.dist-info/METADATA
dataculpa_client-1.4.1.dist-info/WHEEL
dataculpa_client-1.4.1.dist-info/top_level.txt
dataculpa_client-1.4.1.dist-info/RECORD
