Metadata-Version: 2.1
Name: dataculpa-client
Version: 1.4.1
Summary: Python client for Data Culpa APIs
Home-page: https://github.com/Data-Culpa/openclients
Author: Data Culpa, Inc
Author-email: hello@dataculpa.com
License: UNKNOWN
Project-URL: Bug Tracker, https://github.com/Data-Culpa/openclients/issues
Platform: UNKNOWN
Classifier: Programming Language :: Python :: 3
Classifier: License :: OSI Approved :: MIT License
Classifier: Operating System :: OS Independent
Requires-Python: >=3.6
License-File: LICENSE
